Topsis-Shubham-102003109/topsis.py
Topsis_Shubham_102003109/topsis.py
Topsis_Shubham_102003109-1.0.2.dist-info/LICENSE
Topsis_Shubham_102003109-1.0.2.dist-info/METADATA
Topsis_Shubham_102003109-1.0.2.dist-info/WHEEL
Topsis_Shubham_102003109-1.0.2.dist-info/entry_points.txt
Topsis_Shubham_102003109-1.0.2.dist-info/top_level.txt
Topsis_Shubham_102003109-1.0.2.dist-info/RECORD
