Metadata-Version: 2.1
Name: Topsis-Shubham-102003109
Version: 1.0.2
Summary: This is a Python library for handling problems related to Multiple Criteria Decision Making(MCDM)
Home-page: https://github.com/shubhammalhotra1708/Topsis-Shubham-102003109
Download-URL: https://github.com/shubhammalhotra1708/Topsis-Shubham-102003109/archive/refs/tags/v1.0.2.tar.gz
Author: Shubham Malhotra
Author-email: shubhammalhotra012@gmail.com
License: MIT
Classifier: License :: OSI Approved :: MIT License
Classifier: Programming Language :: Python :: 3.6
Classifier: Programming Language :: Python :: 3.7
Classifier: Programming Language :: Python :: 3.8
License-File: LICENSE
Requires-Dist: pandas
